[
    {
        "desc":"+25魔法抗性，+500生命值。 每秒回复自身2.5%的最大生命值。",
        "id":3001
    },
    {
        "desc":"+10%攻击力，+25%攻击速度，+30护甲。 提供25%全能吸血。携带者受到的50%伤害会转而在4秒里作为非致命伤害来持续扣除。 [唯一 - 每位英雄仅限1件]",
        "id":3002
    },
    {
        "desc":"+15%攻击力，+15%攻击速度。+30法力值。 每场战斗一次：在施放一个技能后，在5秒里持续回复共120法力值。",
        "id":3003
    },
    {
        "desc":"+25攻击力，+25%攻击速度，+25%法术强度，+25初始法力值，+25护甲，+25魔抗，+250生命值+25法力值和+25%暴击几率",
        "id":3004
    },
    {
        "desc":"+20护甲，+200生命值。 对携带者造成伤害的敌人们会被施加持续1.5秒的20%冰冷效果。在被施加了来自这件装备的7层冰冷后，攻击者会转而被晕眩，但每15秒仅触发一次。 [唯一 - 每位英雄仅限1件] 冰冷:使攻击速度减缓。 晕眩：不能移动、攻击或施放技能。",
        "id":3005
    },
    {
        "desc":"+20攻击力，+30%暴击几率。携带者的攻击和技能会处决低于12%最大生命值的目标。处决有40%几率掉落1金币。",
        "id":3006
    },
    {
        "desc":"+45法术强度，+30护甲，+30魔抗。每场战斗仅触发一次：在40%生命值时，携带者进入持续3秒的免疫伤害和无法被选取状态。 唯一 - 每位英雄仅限1件",
        "id":3007
    },
    {
        "desc":"+30%攻击速度，+35护甲，+35魔法抗性。战斗开始时：如果邻格内没有己方弈子，获得额外的600生命值。",
        "id":3008
    },
    {
        "desc":"+10%攻击速度，+10护甲，+10魔法抗性，+15%暴击率。召唤一个拥有70%最大生命值并且最大法力值+30%的复制体。你无法给复制体装上装备 复制体会受益于已激活的羁绊 [唯一-每位英雄仅限1件]",
        "id":3009
    },
    {
        "desc":"+15%攻击力，+15%攻击速度，+15法术强度，提供+1距离。持有者的攻击和能力对他们与目标之间的每个六角形造成的伤害提高10%。",
        "id":3010
    },
    {
        "desc":"+50法术强度，+30法力值。战斗开始：持有者向他们的目标发射能量冲击波，标记他们并造成他们最大生命值20%的魔法伤害。 在接下来的10秒内，多造成25%伤害。对被震击目标造成的伤害提升至35%。 [唯一-每位英雄仅限一件]",
        "id":3011
    },
    {
        "desc":"获得1件【铁匠手套】，它每回合都会提供2件临时的奥恩宝物。",
        "id":3012
    },
    {
        "desc":"获得1x你的金币存款的法术强度(在30金币时达到最大值)，并在击杀一名敌人后有40%几率掉落2 金币。",
        "id":3013
    },
    {
        "desc":"在承受伤害时提供1护甲、1魔抗和6生命值，这个效果至多叠加40次。 在满层时，提供2金币。",
        "id":3014
    }
]